perfetto/__init__.py
perfetto/trace_data_checks.py
perfetto/batch_trace_processor/__init__.py
perfetto/batch_trace_processor/api.py
perfetto/batch_trace_processor/platform.py
perfetto/common/exceptions.py
perfetto/common/query_result_iterator.py
perfetto/common/repo_utils.py
perfetto/protos/perfetto/trace/perfetto_trace_pb2.py
perfetto/protos/perfetto/trace/perfetto_trace_pb2.pyi
perfetto/trace_builder/proto_builder.py
perfetto/trace_processor/__init__.py
perfetto/trace_processor/api.py
perfetto/trace_processor/http.py
perfetto/trace_processor/metrics.descriptor
perfetto/trace_processor/platform.py
perfetto/trace_processor/protos.py
perfetto/trace_processor/shell.py
perfetto/trace_processor/trace_processor.descriptor
perfetto/trace_uri_resolver/__init__.py
perfetto/trace_uri_resolver/path.py
perfetto/trace_uri_resolver/registry.py
perfetto/trace_uri_resolver/resolver.py
perfetto/trace_uri_resolver/util.py
perfetto-0.16.0.dist-info/licenses/LICENSE
perfetto-0.16.0.dist-info/METADATA
perfetto-0.16.0.dist-info/WHEEL
perfetto-0.16.0.dist-info/top_level.txt
perfetto-0.16.0.dist-info/RECORD
